{"name": "Sagamihara City Open Data Portal", "description": "Open Data portal of Sagamihara City, providing public datasets related to the municipality.", "owner_name": "Sagamihara City", "owner_website": "https://opendata.city.sagamihara.kanagawa.jp", "owner_type": "Local government", "owner_country_iso2": "JP", "owner_country": "Japan", "owner_subregion_iso3166_2": "JP-14", "owner_subregion_name": "Kanagawa Prefecture", "data_themes": [{"data_theme": "Government and public sector"}, {"data_theme": "Society"}, {"data_theme": "Transport"}, {"data_theme": "Environment"}], "geotopics": [{"iso19115_theme": "society"}, {"iso19115_theme": "transportation"}, {"iso19115_theme": "environment"}], "tags": ["opendata", "government", "local"], "uid": "cdi00001012", "id": "opendatacitysagamiharakanagawajp"}