{"name": "gis.ktn.gv.at/ogd/custom/stac_cat_ktn/STAC_2023/kagis-catalog/catalog.json", "description": "Catalog with geospatial data hosted under the K\u00e4rnten (Carinthia) regional government domain.", "owner_name": "Regional government of K\u00e4rnten (Carinthia)", "owner_website": "https://gis.ktn.gv.at/ogd", "owner_type": "Regional government", "owner_country_iso2": "AT", "owner_country": "Austria", "owner_subregion_iso3166_2": "AT-2", "owner_subregion_name": "Carinthia", "data_themes": ["Environment", "Government and public sector"], "geotopics": [], "tags": ["geospatial", "open data", "Austria", "Carinthia"], "uid": "cdi00000049", "id": "alsrasterkaernten2023"}