{"name": "City of Mesa GIS", "description": "Open GIS Data Site for the City of Mesa, Arizona. The site provides access to publicly-available GIS data.", "owner_name": "City of Mesa, Arizona", "owner_website": "https://opengis.mesaaz.gov/", "owner_type": "Local government", "owner_country_iso2": "US", "owner_country": "United States", "owner_subregion_iso3166_2": "US-AZ", "owner_subregion_name": "Arizona", "data_themes": ["geographical names"], "geotopics": ["imageryBaseMapsEarthCover", "location", "utilitiesCommunication", "transportation", "planningCadastre"], "tags": ["GIS", "geospatial", "open data", "Mesa", "Arizona"], "uid": "cdi00003850", "id": "opengismesaazgov"}