{"name": "Thai Customs Data Catalog", "description": "Official data catalog of the Thai Customs Department.", "owner_name": "Thai Customs Department", "owner_website": "https://www.customs.go.th", "owner_type": "Central government", "owner_country_iso2": "TH", "owner_country": "Thailand", "owner_subregion_iso3166_2": null, "owner_subregion_name": null, "data_themes": ["Trade"], "geotopics": ["Economy"], "tags": ["customs", "tariff", "statistics"], "uid": "cdi00001513", "id": "catalogcustomsgoth"}