{"name": "BCO-DMO", "description": "The BCO-DMO resource catalog offers free and open access to publicly funded research products whose field of study are biological and chemical oceanography.", "owner_name": "Biological and Chemical Oceanography Data Management Office", "owner_website": "https://www.bco-dmo.org", "owner_type": "Academy", "owner_country_iso2": "US", "owner_country": "United States", "owner_subregion_iso3166_2": null, "owner_subregion_name": null, "data_themes": ["Science"], "geotopics": ["oceans", "environment", "biota"], "tags": ["oceanography", "biological", "chemical", "research data", "open access"], "uid": "cdi00004525", "id": "wwwbcodmoorg"}