{"name": "Open Context", "description": "Publisher of archaeological and related research data, images, maps, field notes, 3D models, and more. Information richly describes research, with unique identifiers, DOIs, and links to museum collections.", "owner_name": null, "owner_website": null, "owner_type": "Academy", "owner_country_iso2": null, "owner_country": null, "owner_subregion_iso3166_2": null, "owner_subregion_name": null, "data_themes": ["Science and technology", "Education, culture and sport"], "geotopics": ["Biota", "Geoscientific information", "Environment", "Society", "Location"], "tags": ["archaeology", "research data", "3D models", "maps", "field notes", "media", "doi", "open data"], "uid": "cdi00004361", "id": "opencontextorg"}