{"name": "data.taybac.vnu.edu.vn", "description": "No information available from the provided search results or the given URL content. Fill in if known.", "owner_name": "Tay Bac University", "owner_website": "https://www.utb.edu.vn/en/", "owner_type": "Academy", "owner_country_iso2": "VN", "owner_country": "Vietnam", "owner_subregion_iso3166_2": "VN-21", "owner_subregion_name": "Son La", "data_themes": ["Education", "Science"], "geotopics": ["Economy", "Society"], "tags": [], "uid": "cdi00002471", "id": "datataybacvnueduvn"}