{"name": "Saue valla Geoinfo v\u00e4rav", "description": "Saue valla Geoinfo V\u00e4rav sisaldab endas kaardi ja ruumiandmeid valla ehituse, keskkonna, rahvastiku, kultuuri ja vabaaja veetmise v\u00f5imaluste kohta.", "owner_name": "Saue valla omavalitsus (Saue Municipality)", "owner_website": "https://gis.sauevald.ee", "owner_type": "Local government", "owner_country_iso2": "EE", "owner_country": "Estonia", "owner_subregion_iso3166_2": null, "owner_subregion_name": null, "data_themes": ["environment", "population and society", "government and public sector"], "geotopics": ["boundaries", "elevation", "environment", "geoscientificInformation", "imageryBaseMapsEarthCover", "inlandWaters", "intelligenceMilitary", "location", "planningCadastre", "structure", "transportation", "utilitiesCommunication"], "tags": ["geoinfo", "saue", "estonia"], "uid": "cdi00002358", "id": "gissauevaldee"}