{"name": "Temperate ReefBase - Catalogue", "description": "A data catalog for marine and temperate reef data hosted by IMAS at the University of Tasmania.", "owner_name": "IMAS, University of Tasmania", "owner_website": "https://www.imas.utas.edu.au/", "owner_type": "Academy", "owner_country_iso2": "AU", "owner_country": "Australia", "owner_subregion_iso3166_2": "TAS", "owner_subregion_name": "Tasmania", "data_themes": ["Environment"], "geotopics": ["Oceans", "Environment", "Biota"], "tags": ["marine", "reef", "Australia", "IMAS", "Tasmania"], "uid": "cdi00004916", "id": "cataloguetemperatereefbaseimasutaseduau"}