{"name": "nada.ucc.edu.gh", "description": "Data Catalog - Microdata Home", "owner_name": "University of Cape Coast (UCC) / Institute partners", "owner_website": "https://nada.ucc.edu.gh/index.php/catalog", "owner_type": "Academy", "owner_country_iso2": "GH", "owner_country": "Ghana", "owner_subregion_iso3166_2": "GHA", "owner_subregion_name": "Ghana", "data_themes": ["Economic and Finance", "Education", "Health", "Agriculture", "Population, Census"], "geotopics": ["economy", "society", "health", "farming", "population"], "tags": ["microdata", "survey", "education", "health", "enterprise", "household", "agriculture", "population"], "uid": "cdi00000851", "id": "nadauccedugh"}