{"name": "Falkland Islands Data Portal", "description": "Data portal for the Falkland Islands featuring datasets in categories such as Structure and Transportation.", "owner_name": "SAERI (South Atlantic Environmental Research Institute)", "owner_website": "https://dataportal.saeri.org", "owner_type": "International", "owner_country_iso2": "FK", "owner_country": "Falkland Islands", "owner_subregion_iso3166_2": "FLK", "owner_subregion_name": "Falkland Islands", "data_themes": ["Transportation", "Structure", "Utilities and Communications"], "geotopics": ["Structure", "Transportation", "Utilities"], "tags": ["Open data", "Environment", "Spatial data"], "uid": "cdi00000844", "id": "dataportalsaeriorg"}