{"name": "https://riisp.insp.mx/nada/index.php", "description": "No description available from search results. Data content and scope must be inferred from the context: the hostname 'insp.mx' is likely Instituto Nacional de Salud P\u00fablica (INSP), a Mexican public health institute.", "owner_name": "Instituto Nacional de Salud P\u00fablica (INSP), Mexico", "owner_website": "https://www.insp.mx", "owner_type": "Central government", "owner_country_iso2": "MX", "owner_country": "Mexico", "owner_subregion_iso3166_2": null, "owner_subregion_name": null, "data_themes": ["health"], "geotopics": ["health"], "tags": ["health", "public health", "data catalog"], "uid": "cdi00001135", "id": "riispinspmx"}