{"name": "Maldives Open Data Portal", "description": "A central source of open public data of Maldives. Anyone can access these anonymized data of public interest published here by government agencies and state bodies.", "owner_name": "Maldives Government", "owner_website": "https://beta.data.gov.mv", "owner_type": "Central government", "owner_country_iso2": "MV", "owner_country": "Maldives", "owner_subregion_iso3166_2": null, "owner_subregion_name": null, "data_themes": [{"data_theme": "Government and public sector"}, {"data_theme": "Economy and finance"}, {"data_theme": "Education, culture and sport"}, {"data_theme": "Environment"}, {"data_theme": "Transport"}, {"data_theme": "Science and technology"}, {"data_theme": "Justice, legal system and public safety"}], "geotopics": [{"iso19115_theme": "economy"}, {"iso19115_theme": "environment"}, {"iso19115_theme": "education"}, {"iso19115_theme": "boundaries"}], "tags": ["open data", "government", "Maldives"], "uid": "cdi00004852", "id": "betadatagovmv"}