{"name": "Brandeis ScholarWorks", "description": "Brandeis ScholarWorks preserves and provides access to the research and creative scholarship created by Brandeis faculty, students, and staff. The research papers, theses, dissertations, books, reports, interviews, data and multimedia here represent Brandeis\u2019s rich intellectual and cultural community.", "owner_name": "Brandeis University", "owner_website": "https://www.brandeis.edu", "owner_type": "Academy", "owner_country_iso2": "US", "owner_country": "United States", "owner_subregion_iso3166_2": "US-MA", "owner_subregion_name": "Massachusetts", "data_themes": [], "geotopics": [], "tags": ["research", "thesis", "dissertation", "data", "multimedia", "scholarship", "academia"], "uid": "cdi00004553", "id": "scholarworksbrandeisedu"}