{"name": "Fisheries and Oceans Canada GIS Platform Data Catalog", "description": "ArcGIS REST services data catalog provided by Fisheries and Oceans Canada", "owner_name": "Fisheries and Oceans Canada", "owner_website": "https://gisp.dfo-mpo.gc.ca/arcgis/rest/services", "owner_type": "Central government", "owner_country_iso2": "CA", "owner_country": "Canada", "owner_subregion_iso3166_2": "CA", "owner_subregion_name": "", "data_themes": ["Environment"], "geotopics": ["oceans", "environment", "fisheries", "biota"], "tags": ["GIS", "oceanography", "fisheries", "ArcGIS", "Canada"], "uid": "cdi00004290", "id": "gispdfompogcca"}