{"name": "\u3075\u3058\u306e\u304f\u306b\u30aa\u30fc\u30d7\u30f3\u30c7\u30fc\u30bf\u30ab\u30bf\u30ed\u30b0\uff08Open Data Catalog Shizuoka\uff09", "description": "Prefecture aims to utilize extensive point cloud data and open data for social and urban planning, with a focus on virtual reproductions and digital twins.", "owner_name": "Shizuoka Prefecture", "owner_website": "https://ckan.pref.shizuoka.jp", "owner_type": "Regional government", "owner_country_iso2": "JP", "owner_country": "Japan", "owner_subregion_iso3166_2": "22", "owner_subregion_name": "Shizuoka", "data_themes": ["Government and public sector", "Science and technology", "Environment"], "geotopics": ["environment", "elevation", "structure", "society", "planningCadastre", "transportation"], "tags": ["point cloud", "digital twin", "urban planning"], "uid": "cdi00000988", "id": "ckanprefshizuokajp"}