{"name": "salmon-wa-rco.opendata.arcgis.com", "description": "Data catalog containing geospatial datasets and resources related to salmon and Washington State RCO (Recreation and Conservation Office)", "owner_name": "Washington State Recreation and Conservation Office (RCO)", "owner_website": "https://salmon-wa-rco.opendata.arcgis.com/", "owner_type": "Regional government", "owner_country_iso2": "US", "owner_country": "United States of America", "owner_subregion_iso3166_2": "US-WA", "owner_subregion_name": "Washington", "data_themes": ["environment", "fisheries"], "geotopics": ["environment", "biota", "oceans"], "tags": ["salmon", "conservation", "gis", "environmental data", "habitat", "fisheries"], "uid": "cdi00003950", "id": "salmonwarcoopendataarcgiscom"}