{"name": "Allegheny County Health Department Open Data & Maps Hub", "description": "A public data catalog featuring open data and maps from the Allegheny County Health Department.", "owner_name": "Allegheny County Health Department", "owner_website": "https://public-open-data-and-maps-achd.hub.arcgis.com/", "owner_type": "Local government", "owner_country_iso2": "US", "owner_country": "United States", "owner_subregion_iso3166_2": "US-PA", "owner_subregion_name": "Pennsylvania", "data_themes": null, "geotopics": null, "tags": ["health", "public", "maps", "open data"], "uid": "cdi00003907", "id": "publicopendataandmapsachdhubarcgiscom"}