{"name": "yourdata-unifiedgov.opendata.arcgis.com", "description": "Aggregated data catalog provided presumably by a unified government body, hosting datasets related to various topics.", "owner_name": null, "owner_website": "https://yourdata-unifiedgov.opendata.arcgis.com/", "owner_type": "Central government", "owner_country_iso2": null, "owner_country": null, "owner_subregion_iso3166_2": null, "owner_subregion_name": null, "data_themes": [], "geotopics": [], "tags": [], "uid": "cdi00004109", "id": "yourdataunifiedgovopendataarcgiscom"}