{"name": "data.ballarat.vic.gov.au", "description": "The Ballarat data catalog provides access to local government datasets for the Ballarat region, covering various topics such as infrastructure, planning, and services. Given the URL and available context, the catalog is representative of a local government body.", "owner_name": "City of Ballarat", "owner_website": "https://data.ballarat.vic.gov.au", "owner_type": "Local government", "owner_country_iso2": "AU", "owner_country": "Australia", "owner_subregion_iso3166_2": "AU-VIC", "owner_subregion_name": "Victoria", "data_themes": ["Government and public sector", "Geographical names and administrative units", "Land use", "Transport", "Buildings", "Environment"], "geotopics": ["boundaries", "elevation", "imageryBaseMapsEarthCover", "intelligenceMilitary", "inlandWaters", "location", "planningCadastre", "structure", "transportation", "utilitiesCommunication"], "tags": ["Ballarat", "local government", "open data", "GIS"], "uid": "cdi00000089", "id": "databallaratvicgovau"}