{"name": "Katalog otev\u0159en\u00fdch dat m\u011bsta Opavy (Opava City Data Catalog)", "description": "Katalog otev\u0159en\u00fdch dat m\u011bsta Opavy je port\u00e1l poskytuj\u00edc\u00ed p\u0159ehled o datech vydan\u00fdch m\u011bstem Opavou. Obsahuje r\u016fzn\u00e9 datov\u00e9 sady t\u00fdkaj\u00edc\u00ed se oblasti Opavy, v\u010detn\u011b oblast\u00ed jako je m\u00edstn\u00ed spr\u00e1va, \u017eivotn\u00ed prost\u0159ed\u00ed, doprava a dal\u0161\u00ed aspekty ve\u0159ejn\u00e9ho \u017eivota.", "owner_name": "Statut\u00e1rn\u00ed m\u011bsto Opava", "owner_website": "https://www.opava-city.cz/", "owner_type": "Local government", "owner_country_iso2": "CZ", "owner_country": "\u010cesk\u00e1 republika", "owner_subregion_iso3166_2": "CZ-OP", "owner_subregion_name": "Moravskoslezsk\u00fd kraj", "data_themes": ["Government and public sector", "Regions and cities", "Science, technology and innovation"], "geotopics": ["society", "boundaries", "environment"], "tags": ["Opava", "otev\u0159en\u00e1 data", "ve\u0159ejn\u00e1 spr\u00e1va", "m\u011bstsk\u00e9 \u010d\u00e1sti"], "uid": "cdi00004656", "id": "kodopavacitycz"}