{"name": "eReefs THREDDS Data Server catalogue", "description": "eReefs research project aims to develop a platform providing a comprehensive view of dynamic marine environment conditions across the Great Barrier Reef from end-of-catchments and estuaries to reef lagoons and the open ocean. The system provides information on physical processes, sediment transport, biogeochemistry and ocean colour, addressing enhanced monitoring, data standards, data architecture, operational modelling, reporting and data visualisation.", "owner_name": "Australian Institute of Marine Science", "owner_website": "https://thredds.ereefs.aims.gov.au/thredds/catalog/catalog.html", "owner_type": "Academy", "owner_country_iso2": "AU", "owner_country": "Australia", "owner_subregion_iso3166_2": "AU-QLD", "owner_subregion_name": "Queensland", "data_themes": ["ENVIRONMENT", "OCEANS"], "geotopics": ["OCEANS", "ENVIRONMENT", "GEOSCIENTIFICINFORMATION"], "tags": ["Great Barrier Reef", "hydrodynamics", "sediment", "biogeochemistry", "ocean colour", "NetCDF"], "uid": "cdi00005314", "id": "threddsereefsaimsgovau"}