{"name": "Thua Thien Hue Province Open Data Portal", "description": "The official open data portal of Thua Thien Hue province, Vietnam, making provincial datasets available for public use, supporting transparency and evidence-based policy making.", "owner_name": "Provincial People's Committee of Thua Thien-Hue", "owner_website": "https://data.thuathienhue.gov.vn", "owner_type": "Regional government", "owner_country_iso2": "VN", "owner_country": "Vietnam", "owner_subregion_iso3166_2": "VN-26", "owner_subregion_name": "Thua Thien Hue", "data_themes": [], "geotopics": [], "tags": ["open data", "provincial", "data catalog"], "uid": "cdi00002339", "id": "datathuathienhuegovvn"}