{"name": "Duluth Transit Authority Open Data", "description": "The DTA is undergoing an extensive evaluation of bus stops throughout Duluth and Superior. The goal of the bus stop project is to identify areas where bus stops can be improved.", "owner_name": "Duluth Transit Authority", "owner_website": "https://data-dta-mn.opendata.arcgis.com/", "owner_type": "Local government", "owner_country_iso2": "US", "owner_country": "United States", "owner_subregion_iso3166_2": "US-MN", "owner_subregion_name": "Minnesota", "data_themes": ["Transport"], "geotopics": ["transportation"], "tags": ["bus stops", "transit", "public transportation", "Duluth", "Superior", "ArcGIS"], "uid": "cdi00002899", "id": "datadtamnopendataarcgiscom"}