{"name": "City of Pasadena, CA (Open Data 2.0)", "description": "Welcome! This is the community's public platform for exploring and downloading open data, building apps, and engaging to solve important local issues.", "owner_name": "City of Pasadena", "owner_website": "https://data.cityofpasadena.net/", "owner_type": "Local government", "owner_country_iso2": "US", "owner_country": "United States", "owner_subregion_iso3166_2": "US-CA", "owner_subregion_name": "California", "data_themes": ["Government and public sector", "Transport"], "geotopics": ["Location", "Boundaries", "Transportation networks"], "tags": ["Open Data", "Community Engagement"], "uid": "cdi00002891", "id": "datacityofpasadenanet"}