{"name": "data.hydro.gov.my", "description": "Data catalog by the Department of Survey and Mapping Malaysia (hydrographic, nautical, tide utilities, GIS data)", "owner_name": "Department of Survey and Mapping Malaysia", "owner_website": "https://data.hydro.gov.my", "owner_type": "Central government", "owner_country_iso2": "MY", "owner_country": "Malaysia", "owner_subregion_iso3166_2": "MYS", "owner_subregion_name": "Malaysia", "data_themes": [{"data_theme_code": "ENV", "data_theme_name": "Environment"}, {"data_theme_code": "TRAN", "data_theme_name": "Transport"}], "geotopics": [{"iso19115_theme_code": "elevation", "iso19115_theme_name": "Elevation"}, {"iso19115_theme_code": "environment", "iso19115_theme_name": "Environment"}, {"iso19115_theme_code": "transportation", "iso19115_theme_name": "Transportation"}], "tags": ["hydrographic", "nautical", "tide", "GIS", "Malaysia"], "uid": "cdi00001144", "id": "datahydrogovmy"}