{"name": "GeoServer - Regione Valle d'Aosta", "description": "GeoServer for accessing geospatial data from Regione Valle d'Aosta.", "owner_name": "Regione Autonoma Valle d'Aosta", "owner_website": "https://geoservizi.regione.vda.it/geoserver", "owner_type": "Regional government", "owner_country_iso2": "IT", "owner_country": "Italia", "owner_subregion_iso3166_2": "ITA-VDA", "owner_subregion_name": "Valle d'Aosta", "data_themes": ["Other"], "geotopics": ["geoscientificInformation", "inlandWaters", "boundaries", "environment"], "tags": ["geoserver", "opendata", "geospatial"], "uid": "cdi00004990", "id": "geoserviziregionevdait"}