{"name": "Grant County, MN Hub", "description": "Official ArcGIS Hub site for Grant County, Minnesota, providing access to maps, apps, datasets, and resources.", "owner_name": "Grant County", "owner_website": "https://hub-co-grant-mn-us.hub.arcgis.com/", "owner_type": "Local government", "owner_country_iso2": "US", "owner_country": "United States", "owner_subregion_iso3166_2": "", "owner_subregion_name": "Minnesota", "data_themes": [], "geotopics": [], "tags": [], "uid": "cdi00002959", "id": "hubcograntmnushubarcgiscom"}