{"name": "od.data.gov.sa", "description": "Official data catalog platform for Saudi Arabia, hosting open data from government and public sources, facilitating access to a wide range of public sector datasets for researchers, policy-makers, and citizens", "owner_name": "Saudi Data and AI Authority (SDAIA) / National Data Bank (NDB)", "owner_website": "https://od.data.gov.sa", "owner_type": "Central government", "owner_country_iso2": "SA", "owner_country": "Saudi Arabia", "owner_subregion_iso3166_2": "SA", "owner_subregion_name": "Saudi Arabia", "data_themes": ["Society", "Government and public sector", "Economy", "Geography", "Education, culture and sport", "Environment", "Transport", "Science and technology"], "geotopics": ["biota", "boundaries", "climatologyMeteorologyAtmosphere", "economy", "elevation", "environment", "farming", "geoscientificInformation", "health", "imageryBaseMapsEarthCover", "inlandWaters", "location", "oceans", "planningCadastre", "society", "structure", "transportation", "utilitiesCommunication"], "tags": ["Government data", "Open data", "Saudi Arabia"], "uid": "cdi00001456", "id": "oddatagovsa"}