{"name": "opendata.fcc.gov", "description": "Federal Communications Commission open data catalog", "owner_name": "Federal Communications Commission", "owner_website": "https://opendata.fcc.gov", "owner_type": "Central government", "owner_country_iso2": "US", "owner_country": "United States", "owner_subregion_iso3166_2": null, "owner_subregion_name": null, "data_themes": ["government", "transport", "energy", "communications", "environment", "science"], "geotopics": ["society", "economy", "utilitiesCommunication", "environment", "imageryBaseMapsEarthCover", "inlandWaters"], "tags": ["FCC", "broadband", "telecom", "spectrum", "consumer complaints", "licensing"], "uid": "cdi00001638", "id": "opendatafccgov"}