{"name": "Pacific Data Hub - ncWMS (tds.pacificdata.org/ncWMS/)", "description": "Data catalog providing access to geospatial datasets via ncWMS, presumably under regional or international management.", "owner_name": "Pacific Data Hub", "owner_website": "https://tds.pacificdata.org/ncWMS/", "owner_type": "International", "owner_country_iso2": "", "owner_country": "Pacific region (multiple countries)", "owner_subregion_iso3166_2": "", "owner_subregion_name": "Pacific Islands", "data_themes": ["Environment"], "geotopics": ["Oceans", "ClimatologyMeteorologyAtmosphere"], "tags": ["geospatial", "WMS", "Pacific", "ncWMS"], "uid": "cdi00005061", "id": "tdspacificdataorgncwms"}