{"name": "AURIN Data Catalogue", "description": "A national research infrastructure providing urban and regional planning data and tools, offering access to thousands of datasets from diverse research disciplines and data visualisation tools.", "owner_name": "Australian Urban Research Infrastructure Network (AURIN)", "owner_website": "https://data.aurin.org.au", "owner_type": "Academy", "owner_country_iso2": "AU", "owner_country": "Australia", "owner_subregion_iso3166_2": "AU-VIC", "owner_subregion_name": "Victoria", "data_themes": ["GOVERNMENT_PUBLIC_SECTOR", "REGIONAL_AND_URBAN_DEVELOPMENT", "TRANSPORT", "HEALTH", "POPULATION_AND_SOCIETY"], "geotopics": ["boundaries", "elevation", "imageryBaseMapsEarthCover", "location", "planningCadastre", "society", "transportation"], "tags": ["urban research", "planning", "GIS", "spatial data", "Australia"], "uid": "cdi00000088", "id": "dataaurinorgau"}