{"name": "Extract from invester-i-slagelse-gammel-slagelse.hub.arcgis.com", "description": "Precise extraction of data catalog metadata based on provided vocabularies.", "owner_name": null, "owner_website": "https://invester-i-slagelse-gammel-slagelse.hub.arcgis.com/", "owner_type": "Local government", "owner_country_iso2": "DK", "owner_country": "Denmark", "owner_subregion_iso3166_2": "DK-83 (Region Sj\u00e6lland)", "owner_subregion_name": "Slagelse", "data_themes": [], "geotopics": [], "tags": ["Slagelse", "investments", "planning", "municipality"], "uid": "cdi00002975", "id": "investerislagelsegammelslagelsehubarcgiscom"}