{"name": "Reposit\u00f3rio Polen", "description": "Research Data Repository Service under development by FCCN, aiming to support the needs of the scientific and teaching community in Portugal regarding Research Data Management (RDM) and promoting Open Science through data sharing and preservation, particularly for publicly funded projects.", "owner_name": "FCT (Foundation for Science and Technology) / FCCN (Unit FCCN)", "owner_website": "https://repositorio.polen.fccn.pt", "owner_type": "Central government", "owner_country_iso2": "PT", "owner_country": "Portugal", "owner_subregion_iso3166_2": "", "owner_subregion_name": "", "data_themes": ["science", "research"], "geotopics": ["location", "society"], "tags": ["Research Data Management", "Open Science", "FAIR principles"], "uid": "cdi00001330", "id": "repositoriopolenfccnpt"}