{"name": "MapBiomas Dataverse", "description": "Data catalog providing access to land cover and land use maps derived from satellite imagery and periodic classifications, with dynamic and procedural updates to reflect improvements in classification algorithms.", "owner_name": "MapBiomas", "owner_website": "https://mapbiomas.org", "owner_type": "Civil society", "owner_country_iso2": "BR", "owner_country": "Brazil", "owner_subregion_iso3166_2": "BR", "owner_subregion_name": "", "data_themes": ["Land Use::Land Cover"], "geotopics": ["imageryBaseMapsEarthCover", "environment", "planningCadastre"], "tags": ["land cover", "land use", "satellite imagery", "classification"], "uid": "cdi00000257", "id": "dataversemapbiomasorg"}