{"name": "GeoServer - prod.ogsl.ca", "description": "Canadian GeoServer hosting environment for geospatial data by OGSL (Open Geospatial Standards Laboratory)", "owner_name": "OGSL (Open Geospatial Standards Laboratory)", "owner_website": "https://ogsl.ca/", "owner_type": "Academy", "owner_country_iso2": "CA", "owner_country": "Canada", "owner_subregion_iso3166_2": null, "owner_subregion_name": null, "data_themes": ["http://publications.europa.eu/resource/authority/data-theme/ENVI"], "geotopics": ["http://www.isotc211.org/2005/iso19115/-3/mri/1.0/code/geographicName/Oceans", "http://www.isotc211.org/2005/iso19115/-3/mri/1.0/code/geographicName/Coastlines", "http://www.isotc211.org/2005/iso19115/-3/mri/1.0/code/geographicName/Climate", "http://www.isotc211.org/2005/iso19115/-3/mri/1.0/code/geographicName/Environment"], "tags": ["geoserver", "geospatial", "ocean", "coastline", "climate", "environment"], "uid": "temp00003435", "id": "geoserverprodogslca"}