{"name": "Open Data - Comune di Firenze", "description": "Il portale italiano degli open data raccoglie i dati aperti del Ministero per la PA e l'Innovazione e di numerose Amministrazioni centrali e territoriali, per mettere a disposizione dei cittadini e del mercato dati in formato aperto e per stimolare l'utilizzo di questi dati in applicazioni che rendano pi\u00f9 facile la vita di cittadini ed imprese.", "owner_name": "Comune di Firenze", "owner_website": "https://opendata.comune.fi.it", "owner_type": "Local government", "owner_country_iso2": "IT", "owner_country": "Italy", "owner_subregion_iso3166_2": "IT-52", "owner_subregion_name": "Toscana", "data_themes": ["ENVI", "AGRI", "ENER", "TRAN", "SOCI", "ECON", "REGI", "GOVE", "JUST", "EDUC", "HEAL", "ENVI"], "geotopics": ["boundaries", "climatologyMeteorologyAtmosphere", "economy", "elevation", "environment", "geoscientificInformation", "health", "imageryBaseMapsEarthCover", "intelligenceMilitary", "inlandWaters", "location", "oceans", "planningCadastre", "society", "structure", "transportation", "utilitiesCommunication"], "tags": ["open data", "Comune di Firenze", "statistica", "anagrafica", "ambiente", "mobilit\u00e0", "spazi pubblici", "zona 30"], "uid": "temp00002962", "id": "opendatacomunefiit"}