{"name": "mapas.munialajuela.go.cr", "description": "REST services endpoint for geospatial data hosted by the Municipality of Alajuela, Costa Rica", "owner_name": "Municipality of Alajuela", "owner_website": "https://mapas.munialajuela.go.cr", "owner_type": "Local government", "owner_country_iso2": "CR", "owner_country": "Costa Rica", "owner_subregion_iso3166_2": "", "owner_subregion_name": "Alajuela", "data_themes": [], "geotopics": [], "tags": ["GIS", "REST", "spatial data", "local government"], "uid": "temp00005871", "id": "mapasmunialajuelagocr"}