{"name": "geoweb.amstelveen.nl/geoserver", "description": "Data catalog exposing geospatial datasets and services via GeoServer.", "owner_name": null, "owner_website": null, "owner_type": "Local government", "owner_country_iso2": "NL", "owner_country": "Netherlands", "owner_subregion_iso3166_2": null, "owner_subregion_name": null, "data_themes": ["TRANSPORT", "ENVIRONMENT", "PLANNING_CADASTRE"], "geotopics": ["boundaries", "elevation", "environment", "geoscientificInformation", "imageryBaseMapsEarthCover", "inlandWaters", "location", "planningCadastre", "structure", "transportation", "utilitiesCommunication"], "tags": ["geoserver", "geodata", "Amstelveen", "Netherlands"], "uid": "temp00005267", "id": "geowebamstelveennl"}