{"name": "https://app.geonue.com/geoserver", "description": "GeoServer data catalog", "owner_name": "GeoServer", "owner_website": "https://app.geonue.com/geoserver", "owner_type": "Central government", "owner_country_iso2": "IT", "owner_country": "Italy", "owner_subregion_iso3166_2": "RN", "owner_subregion_name": "Rimini", "data_themes": ["geographical information systems", "other"], "geotopics": ["geoscientificInformation", "location", "inlandWaters"], "tags": ["geospatial", "web services", "open data", "catalog"], "uid": "temp00001701", "id": "appgeonuecom"}