{"name": "ENARGAS Geographic Information System REST Services", "description": "REST-based geospatial services provided by ENARGAS, the Argentine National Gas Regulatory Entity.", "owner_name": "ENARGAS", "owner_website": "https://sig.enargas.gov.ar", "owner_type": "Central government", "owner_country_iso2": "AR", "owner_country": "Argentina", "owner_subregion_iso3166_2": "ARG", "owner_subregion_name": "Argentina", "data_themes": ["ENVIRONMENT"], "geotopics": ["geoscientificInformation"], "tags": ["gas", "infrastructure", "REST", "Argentina"], "uid": "temp00005861", "id": "sigenargasgovar"}