{"name": "PNG Geoportal", "description": "Data catalog providing access to GIS and spatial datasets related to Papua New Guinea, including digital atlases, interactive spatial data viewers, and open access geospatial data repositories.", "owner_name": "Papua New Guinea Environment", "owner_website": "https://png-geoportal.org", "owner_type": "Central government", "owner_country_iso2": "PG", "owner_country": "Papua New Guinea", "owner_subregion_iso3166_2": "OC", "owner_subregion_name": "Oceania", "data_themes": ["geographical"], "geotopics": ["environment", "geoscientificInformation", "elevation", "imageryBaseMapsEarthCover"], "tags": ["GIS", "spatial data", "geoportal", "Pacific", "environment"], "uid": "temp00000830", "id": "pnggeoportalorg"}