{"name": "https://gistest.saskatchewan.ca/arcgis/rest/services", "description": "Web mapping and GIS REST services managed by the Government of Saskatchewan.", "owner_name": "Government of Saskatchewan", "owner_website": "https://gistest.saskatchewan.ca/arcgis/rest/services", "owner_type": "Regional government", "owner_country_iso2": "CA", "owner_country": "Canada", "owner_subregion_iso3166_2": "CA-SK", "owner_subregion_name": "Saskatchewan", "data_themes": ["TRANSPORT", "ENVIRONMENT", "GOVERNMENT_PUBLIC_SECTOR"], "geotopics": ["location", "environment", "society"], "tags": ["GIS", "geospatial data", "map services", "government data", "Saskatchewan"], "uid": "temp00001305", "id": "gistestsaskatchewanca"}