{"name": "http://geoportal.okutimurkab.go.id/geoserver", "description": "Geoportal providing geospatial data services via GeoServer.", "owner_name": "Okutimur Kabupaten (assuming local government, based on URL and standard practice for Indonesian regional geoportals)", "owner_website": "http://geoportal.okutimurkab.go.id", "owner_type": "Local government", "owner_country_iso2": "ID", "owner_country": "Indonesia", "owner_subregion_iso3166_2": null, "owner_subregion_name": "Okutimur Kabupaten (assumed based on URL and context)", "data_themes": ["Inspire themes (geospatial data themes), but as specific DCAT-AP themes not specified, using 'http://publications.europa.eu/resource/authority/data-theme/GEOC' (geospatial)"], "geotopics": [{"iso19115_theme": "geoscientificInformation"}, {"iso19115_theme": "boundaries"}, {"iso19115_theme": "location"}, {"iso19115_theme": "planningCadastre"}], "tags": ["geospatial", "GIS", "GeoServer"], "uid": "temp00005123", "id": "geoportalokutimurkabgoid"}