{"name": "City of Chicago - Data Portal", "description": "The City of Chicago's Data Portal is dedicated to promoting access to government data and encouraging the development of creative tools to engage and serve Chicago's diverse community. The site hosts over 600 datasets presented in easy-to-use formats about City departments, services, facilities and performance.", "owner_name": "City of Chicago", "owner_website": "https://cityofchicago-v2.demo.socrata.com", "owner_type": "Local government", "owner_country_iso2": "US", "owner_country": "United States", "owner_subregion_iso3166_2": "US-IL", "owner_subregion_name": "Illinois", "data_themes": ["administration", "artsAndCulture", "budgetAndManagement", "transportation", "publicSafety", "publicHealth", "humanServices", "publicWorks", "landUse", "statistics", "environment", "finance", "education"], "geotopics": ["boundaries", "economy", "environment", "health", "location", "society", "structure", "transportation"], "tags": ["open data", "government", "datasets", "Chicago", "local government", "public sector"], "uid": "temp00002475", "id": "cityofchicagov2demosocratacom"}