{"name": "Geophysical Data Canada", "description": "A data catalog serving as a central hub for geophysical data and related resources for Canada, managed by Natural Resources Canada.", "owner_name": "Natural Resources Canada", "owner_website": "https://geophysical-data.canada.ca", "owner_type": "Central government", "owner_country_iso2": "CA", "owner_country": "Canada", "owner_subregion_iso3166_2": null, "owner_subregion_name": null, "data_themes": ["Geology", "Earth science"], "geotopics": ["geoscientificInformation"], "tags": ["Geophysical", "Geology", "Canada", "Data Catalog"], "uid": "temp00002031", "id": "geophysicaldatacanadaca"}