{"name": "UniData - Bicocca Data Archive", "description": "UniData is an interdepartmental center of the University of Milan-Bicocca, serving as the Italian point of reference for research data archiving and dissemination, following the model of major European national archives. It manages scientific and statistical data, particularly survey datasets such as Eurostat, ISSP, Istat, WVS, and Eurobarometer, and ensures open access according to data producer agreements.", "owner_name": "University of Milan-Bicocca", "owner_website": "https://www.unidata.unimib.it", "owner_type": "Academy", "owner_country_iso2": "IT", "owner_country": "Italy", "owner_subregion_iso3166_2": "", "owner_subregion_name": "Lombardy", "data_themes": ["Education, culture and sport", "Agriculture, fisheries, forestry and food", "Economy and finance", "Education, training, learning outcomes and qualifications", "Environment", "Government and public sector", "Health", "Justice, legal system and public safety", "Population and society", "Science and technology", "Transport"], "geotopics": ["society"], "tags": ["survey data", "research datasets", "sociology", "statistics", "Eurostat", "ISSP", "Istat", "WVS", "Eurobarometer", "open access"], "uid": "temp00002090", "id": "wwwunidataunimibit"}