{"name": "datos.tsjbaires.gov.ar", "description": "Data catalog of the Tribunal Superior de Justicia de la Ciudad de Buenos Aires, with datasets such as staff rosters and salary scales.", "owner_name": "Tribunal Superior de Justicia de la Ciudad", "owner_website": "https://datos.tsjbaires.gov.ar", "owner_type": "Local government", "owner_country_iso2": "AR", "owner_country": "Argentina", "owner_subregion_iso3166_2": "AR-C", "owner_subregion_name": "Ciudad de Buenos Aires", "data_themes": ["Government and public sector", "Justice, legal system and public safety"], "geotopics": ["society"], "tags": ["justice", "salary", "government"], "uid": "temp00004480", "id": "datostsjbairesgovar"}