{"name": "Geoserver Padang Pariaman Kabupaten", "description": "Geoserver for the Kabupaten Padang Pariaman region under Ina-SDI framework.", "owner_name": "Kabupaten Padang Pariaman / Ina-SDI", "owner_website": "http://padangpariamankab.ina-sdi.or.id/geoserver", "owner_type": "Local government", "owner_country_iso2": "ID", "owner_country": "Indonesia", "owner_subregion_iso3166_2": "ID-SB", "owner_subregion_name": "Sumatera Barat (West Sumatra)", "data_themes": [], "geotopics": [], "tags": ["Geoserver", "Geospatial", "Ina-SDI"], "uid": "temp00005194", "id": "padangpariamankabinasdiorid"}