{"name": "geonode.recette.oieau.fr", "description": "Geoportal managed by GeoNode platform, used for the management and publication of geospatial data.", "owner_name": "", "owner_website": "", "owner_type": "Central government", "owner_country_iso2": "FR", "owner_country": "France", "owner_subregion_iso3166_2": "", "owner_subregion_name": "", "data_themes": ["Environment"], "geotopics": ["Environment"], "tags": ["geonode", "geospatial", "oieau"], "uid": "temp00000297", "id": "geonoderecetteoieaufr"}