{"name": "GeoServer at rechidr.neuquen.gov.ar", "description": "GeoServer data catalog hosted by the Government of Neuqu\u00e9n, Argentina", "owner_name": "Government of Neuqu\u00e9n", "owner_website": "http://rechidr.neuquen.gov.ar:8080/geoserver", "owner_type": "Local government", "owner_country_iso2": "AR", "owner_country": "Argentina", "owner_subregion_iso3166_2": "AR-Q", "owner_subregion_name": "Neuqu\u00e9n", "data_themes": [], "geotopics": [], "tags": ["GIS", "Geospatial", "GeoServer"], "uid": "temp00001217", "id": "rechidrneuquengovar"}