{"name": "ODJFS Data Portal", "description": "An online system where you can request data related to the various JFS programs or access published publicly available data.", "owner_name": "Ohio Department of Job & Family Services (ODJFS)", "owner_website": "https://jfs.ohio.gov", "owner_type": "Central government", "owner_country_iso2": "US", "owner_country": "United States of America", "owner_subregion_iso3166_2": "US-OH", "owner_subregion_name": "Ohio", "data_themes": ["Government and public sector", "Population and society"], "geotopics": ["society"], "tags": ["social services", "statistics", "government data"], "uid": "temp00002849", "id": "datajfsohiogov"}