{"name": "Geoserver at ZVNE, FER HR", "description": "Web interface for accessing geospatial data and services provided by ZVNE, FER HR", "owner_name": "Zavod za vode, naselja i ekologiju, Fakultet elektrotehnike i ra\u010dunarstva", "owner_website": "https://apply.zvne.fer.hr/", "owner_type": "Academy", "owner_country_iso2": "HR", "owner_country": "Croatia", "owner_subregion_iso3166_2": "HR-21", "owner_subregion_name": "City of Zagreb", "data_themes": ["ENVI", "GOVE", "TECH"], "geotopics": ["society", "environment", "imageryBaseMapsEarthCover"], "tags": ["geospatial", "OGC", "GIS", "WMS", "WFS", "catalog"], "uid": "temp00000341", "id": "applyzvneferhr"}