{"name": "geonetwork.alpinesoils.eu", "description": "GeoNetwork data catalog for Alpine soils and related geographical information.", "owner_name": "Not specified", "owner_website": "https://geonetwork.alpinesoils.eu/geonetwork", "owner_type": "Academy", "owner_country_iso2": null, "owner_country": null, "owner_subregion_iso3166_2": null, "owner_subregion_name": null, "data_themes": ["Environment", "Land use", "Agriculture, forestry, fisheries"], "geotopics": ["farming", "environment", "inlandWaters"], "tags": ["soil", "alpine", "geospatial", "ecology", "agriculture"], "uid": "temp00003005", "id": "geonetworkalpinesoilseu"}