{"name": "GeoServer Stuttgart", "description": "GeoServer-based data catalog operated by the city of Stuttgart", "owner_name": "City of Stuttgart", "owner_website": "https://geoserver.stuttgart.de/geoserver", "owner_type": "Local government", "owner_country_iso2": "DE", "owner_country": "Germany", "owner_subregion_iso3166_2": "DE-BW", "owner_subregion_name": "Baden-W\u00fcrttemberg", "data_themes": ["geospatial"], "geotopics": ["location"], "tags": ["geoserver", "opendata", "city", "gis"], "uid": "temp00003507", "id": "geoserverstuttgartde"}