{"name": "Fort Smith Open Data Catalog", "description": "Official open data catalog for the City of Fort Smith, AR, providing geospatial, utility, and city-related datasets for public and staff access.", "owner_name": "City of Fort Smith", "owner_website": "http://opendata.fortsmithar.gov", "owner_type": "Local government", "owner_country_iso2": "US", "owner_country": "United States", "owner_subregion_iso3166_2": "US-AR", "owner_subregion_name": "Arkansas", "data_themes": ["Government and public sector", "Environment", "Transportation"], "geotopics": ["Boundaries", "Utilities communication", "Transportation", "Location"], "tags": ["GIS", "geospatial", "Open Data", "Fort Smith", "Arkansas"], "uid": "temp00002873", "id": "opendatafortsmithargov"}