{"name": "gisportal.dmr.go.th/arcgis/rest/services", "description": "GIS Portal of the Department of Mineral Resources (DMR) hosting various REST map and feature services for geological and mineral resources data", "owner_name": "Department of Mineral Resources", "owner_website": "https://www.dmr.go.th/en/", "owner_type": "Central government", "owner_country_iso2": "TH", "owner_country": "Thailand", "owner_subregion_iso3166_2": "SEA", "owner_subregion_name": "Southeast Asia", "data_themes": ["geology", "environment"], "geotopics": ["geoscientificInformation"], "tags": ["geology", "mineral resources", "GIS", "Thailand"], "uid": "temp00005428", "id": "gisportaldmrgoth"}