{"name": "GeoServer Data Catalog", "description": "A data catalog providing access to geospatial datasets via the GeoServer platform.", "owner_name": "GeoServer", "owner_website": "http://36.66.197.98:8080/geoserver", "owner_type": "Business", "owner_country_iso2": "", "owner_country": "", "owner_subregion_iso3166_2": "", "owner_subregion_name": "", "data_themes": ["Not available"], "geotopics": ["Not available"], "tags": ["geospatial", "GIS", "data catalog"], "uid": "temp00005343", "id": "366619798"}