{"name": "gis.govmin.gl/geoserver/web", "description": "Website provides access to geospatial data through GeoServer, functioning as a data catalog. Specific dataset or catalog descriptions must be determined from the metadata or content at the provided URL.", "owner_name": null, "owner_website": "https://gis.govmin.gl/geoserver/web/", "owner_type": "Central government", "owner_country_iso2": "GL", "owner_country": "Greenland", "owner_subregion_iso3166_2": null, "owner_subregion_name": null, "data_themes": [], "geotopics": [], "tags": ["geospatial", "open data", "GeoServer"], "uid": "temp00001533", "id": "gisgovmingl"}