{"name": "GeoServer Training - Astun Technology", "description": "A two day introduction to GeoServer. Prior GIS experience and an understanding of OGC Web Services is a prerequisite for this GeoServer training course.", "owner_name": "Astun Technology", "owner_website": "https://www.astuntechnology.com/", "owner_type": "Business", "owner_country_iso2": "GB", "owner_country": "United Kingdom", "owner_subregion_iso3166_2": null, "owner_subregion_name": null, "data_themes": ["Education", "Technology"], "geotopics": ["Intellectual property and copyright", "Legal and administrative"], "tags": ["GeoServer", "GIS", "training", "OGC Web Services"], "uid": "temp00004085", "id": "wwwastuntechnologycom"}