{"name": "havplan.dk/geoserver", "description": "Geospatial data and mapping resources for Denmark's marine and coastal planning.", "owner_name": "Danmarks Havplan", "owner_website": "https://havplan.dk/geoserver", "owner_type": "Central government", "owner_country_iso2": "DK", "owner_country": "Denmark", "owner_subregion_iso3166_2": null, "owner_subregion_name": null, "data_themes": ["Environment", "Geographical"], "geotopics": ["environment", "oceans"], "tags": ["geospatial", "marine", "planning"], "uid": "temp00001423", "id": "havplandk"}