{"name": "San Bernardino County Health Statistics Data Catalog", "description": "Interactive data resources for health topics in San Bernardino County, including disease burden, vaccination rates, community health needs, and weekly morbidity and mortality reports.", "owner_name": "San Bernardino County Department of Public Health", "owner_website": "https://healthstat.dph.sbcounty.gov", "owner_type": "Local government", "owner_country_iso2": "US", "owner_country": "United States of America", "owner_subregion_iso3166_2": "US-CA", "owner_subregion_name": "California", "data_themes": ["health"], "geotopics": ["health"], "tags": ["public health", "statistics", "disease burden", "vaccination", "community health"], "uid": "temp00002545", "id": "healthstatdphsbcountygov"}