{"name": "Cartes Ville de Sherbrooke REST Services Catalog", "description": "ArcGIS REST endpoint providing geospatial data services for the City of Sherbrooke", "owner_name": "Ville de Sherbrooke", "owner_website": "https://cartes.ville.sherbrooke.qc.ca/arcgis/rest/services", "owner_type": "Local government", "owner_country_iso2": "CA", "owner_country": "Canada", "owner_subregion_iso3166_2": "QC", "owner_subregion_name": "Quebec", "data_themes": ["transportation", "environment", "planning", "geographical"], "geotopics": ["planningCadastre", "transportation", "elevation", "imageryBaseMapsEarthCover", "inlandWaters", "structures", "utilitiesCommunication", "society"], "tags": ["GIS", "map", "city", "infrastructure", "land use", "base map"], "uid": "temp00003432", "id": "cartesvillesherbrookeqcca"}