{"name": "Geological Survey of Norway (NGU) - Geoserver Web Interface", "description": "Web interface for the Geological Survey of Norway's (NGU) Geoserver, providing access to geospatial datasets.", "owner_name": "Geological Survey of Norway (NGU)", "owner_website": "https://www.ngu.no/", "owner_type": "Central government", "owner_country_iso2": "NO", "owner_country": "Norway", "owner_subregion_iso3166_2": "NOR", "owner_subregion_name": "Norway mainland", "data_themes": ["geology", "environment", "geography"], "geotopics": ["geoscientificInformation"], "tags": ["geoserver", "spatial data", "NGU", "Norway", "geology"], "uid": "temp00000525", "id": "geonguno"}