{"name": "No dataset or metadata found in provided URL", "description": "Extraction from the provided URL did not yield structured dataset or metadata for analysis. No public data catalogs or API responses available; the site may require further access or is not a standard open data catalog based on current retrieval.", "owner_name": "No owner identified", "owner_website": "https://www.ahsz.gov.cn", "owner_type": "Local government", "owner_country_iso2": "CN", "owner_country": "China", "owner_subregion_iso3166_2": "CN-AH", "owner_subregion_name": "Anhui", "data_themes": [], "geotopics": [], "tags": [], "uid": "temp00000152", "id": "wwwahszgovcn"}