{"name": "Geological Society of America Research Repository", "description": "Repository hosting supplemental materials, data, and research outputs for Geological Society of America, such as papers, datasets, and figures.", "owner_name": "Geological Society of America", "owner_website": "https://gsapubs.figshare.com", "owner_type": "Academy", "owner_country_iso2": "US", "owner_country": "United States", "owner_subregion_iso3166_2": "USA", "owner_subregion_name": "United States", "data_themes": ["Science, technology and innovation"], "geotopics": ["Geoscientific information"], "tags": ["geology", "supplemental data", "Figshare"], "uid": "temp00004227", "id": "gsapubsfigsharecom"}